chordauth/.DS_Store
chordauth/AdminDashboard.py
chordauth/CLI.py
chordauth/ChordAuth.py
chordauth/FlaskApp.py
chordauth/__init__.py
chordauth/templates/dashboard.html
chordauth-1.1.1.dist-info/LICENSE
chordauth-1.1.1.dist-info/METADATA
chordauth-1.1.1.dist-info/WHEEL
chordauth-1.1.1.dist-info/entry_points.txt
chordauth-1.1.1.dist-info/RECORD
