Metadata-Version: 2.3
Name: chordauth
Version: 1.1.1
Summary: ChordAuth is a decentralized authenticiation and storage system.
License: MIT
Author: SeafoodStudios
Requires-Python: >=3.11,<4
Classifier: License :: OSI Approved :: MIT License
Classifier: Programming Language :: Python :: 3
Classifier: Programming Language :: Python :: 3.11
Classifier: Programming Language :: Python :: 3.12
Classifier: Programming Language :: Python :: 3.13
Requires-Dist: cryptography (>=45.0.6,<46.0.0)
Requires-Dist: filelock (>=3.18.0,<4.0.0)
Requires-Dist: flask (>=3.1.1,<4.0.0)
Requires-Dist: flask-limiter (>=3.12,<4.0)
Requires-Dist: pinggy (>=0.0.14,<0.0.15)
Requires-Dist: pycryptodome (>=3.17,<4.0)
Requires-Dist: pyopenssl (>=25.1.0,<26.0.0)
Requires-Dist: pyperclip (>=1.9.0,<2.0.0)
Requires-Dist: requests (>=2.32.4,<3.0.0)
Requires-Dist: rsa (>=4.9.1,<5.0.0)
Requires-Dist: waitress (>=3.0.2,<4.0.0)
Requires-Dist: werkzeug (>=3.1.3,<4.0.0)
